[
  {
    "ContainingType": "OnlineStore.API.Controllers.AccountController",
    "Method": "Login",
    "RelativePath": "api/Account/Login",
    "HttpMethod": "POST",
    "IsController": true,
    "Order": 0,
    "Parameters": [
      {
        "Name": "loginUserDTO",
        "Type": "OnlineStore.Service.DTOs.LoginUserDTO",
        "IsRequired": true
      }
    ],
    "ReturnTypes": []
  },
  {
    "ContainingType": "OnlineStore.API.Controllers.AccountController",
    "Method": "Regsiter",
    "RelativePath": "api/Account/Register",
    "HttpMethod": "POST",
    "IsController": true,
    "Order": 0,
    "Parameters": [
      {
        "Name": "registerUserDTO",
        "Type": "OnlineStore.Service.DTOs.RegisterUserDTO",
        "IsRequired": true
      }
    ],
    "ReturnTypes": []
  },
  {
    "ContainingType": "OnlineStore.API.Controllers.CategoriesController",
    "Method": "Categories",
    "RelativePath": "api/Categories",
    "HttpMethod": "GET",
    "IsController": true,
    "Order": 0,
    "Parameters": [],
    "ReturnTypes": []
  }
]